{"basicin_formation": {"candlestick": {"1m": [{"t": 202303150901, "o": 42.25, "h": 42.25, "l": 42.25, "c": 42.25, "v": 5}, {"t": 202303150904, "o": 42.35, "h": 42.45, "l": 42.35, "c": 42.45, "v": 7}, {"t": 202303150906, "o": 42.3, "h": 42.3, "l": 42.1, "c": 42.1, "v": 22}, {"t": 202303150911, "o": 42.15, "h": 42.15, "l": 42, "c": 42, "v": 9}, {"t": 202303150912, "o": 42, "h": 42, "l": 42, "c": 42, "v": 1}, {"t": 202303150913, "o": 41.95, "h": 41.95, "l": 41.8, "c": 41.8, "v": 13}, {"t": 202303150914, "o": 41.85, "h": 41.85, "l": 41.85, "c": 41.85, "v": 1}, {"t": 202303150915, "o": 41.9, "h": 42, "l": 41.85, "c": 41.9, "v": 9}, {"t": 202303150916, "o": 41.9, "h": 41.9, "l": 41.9, "c": 41.9, "v": 1}, {"t": 202303150917, "o": 41.9, "h": 41.9, "l": 41.9, "c": 41.9, "v": 1}, {"t": 202303150918, "o": 41.9, "h": 41.9, "l": 41.9, "c": 41.9, "v": 2}, {"t": 202303150919, "o": 41.9, "h": 41.95, "l": 41.9, "c": 41.95, "v": 5}, {"t": 202303150920, "o": 42, "h": 42, "l": 42, "c": 42, "v": 1}, {"t": 202303150921, "o": 42.1, "h": 42.2, "l": 42.1, "c": 42.2, "v": 4}, {"t": 202303150922, "o": 42.15, "h": 42.15, "l": 42.15, "c": 42.15, "v": 2}, {"t": 202303150923, "o": 42.25, "h": 42.3, "l": 42.25, "c": 42.3, "v": 12}, {"t": 202303150925, "o": 42.35, "h": 42.35, "l": 42.35, "c": 42.35, "v": 5}, {"t": 202303150926, "o": 42.3, "h": 42.3, "l": 42.3, "c": 42.3, "v": 6}, {"t": 202303150928, "o": 42.35, "h": 42.4, "l": 42.35, "c": 42.4, "v": 10}, {"t": 202303150930, "o": 42.3, "h": 42.3, "l": 42.3, "c": 42.3, "v": 1}, {"t": 202303150933, "o": 42.35, "h": 42.35, "l": 42.35, "c": 42.35, "v": 1}, {"t": 202303150938, "o": 42.3, "h": 42.45, "l": 42.25, "c": 42.45, "v": 9}, {"t": 202303150946, "o": 42.4, "h": 42.4, "l": 42.4, "c": 42.4, "v": 3}, {"t": 202303150948, "o": 42.35, "h": 42.35, "l": 42.35, "c": 42.35, "v": 1}, {"t": 202303150949, "o": 42.3, "h": 42.3, "l": 42.3, "c": 42.3, "v": 1}, {"t": 202303150953, "o": 42.2, "h": 42.2, "l": 42.2, "c": 42.2, "v": 5}, {"t": 202303150957, "o": 42.2, "h": 42.4, "l": 42.05, "c": 42.4, "v": 19}, {"t": 202303151016, "o": 42.1, "h": 42.1, "l": 42.1, "c": 42.1, "v": 4}, {"t": 202303151023, "o": 42.25, "h": 42.3, "l": 42.25, "c": 42.3, "v": 3}, {"t": 202303151024, "o": 42.2, "h": 42.2, "l": 42.2, "c": 42.2, "v": 1}, {"t": 202303151027, "o": 42.2, "h": 42.35, "l": 42.2, "c": 42.35, "v": 12}, {"t": 202303151032, "o": 42.2, "h": 42.2, "l": 42.2, "c": 42.2, "v": 3}, {"t": 202303151040, "o": 42.3, "h": 42.3, "l": 42.3, "c": 42.3, "v": 2}, {"t": 202303151057, "o": 42.15, "h": 42.15, "l": 42.15, "c": 42.15, "v": 6}, {"t": 202303151103, "o": 42.1, "h": 42.1, "l": 42.1, "c": 42.1, "v": 1}, {"t": 202303151104, "o": 42.15, "h": 42.2, "l": 42.15, "c": 42.2, "v": 6}, {"t": 202303151110, "o": 42.1, "h": 42.1, "l": 42.1, "c": 42.1, "v": 6}, {"t": 202303151117, "o": 42.1, "h": 42.1, "l": 42.1, "c": 42.1, "v": 1}, {"t": 202303151121, "o": 42.1, "h": 42.15, "l": 42, "c": 42.15, "v": 32}, {"t": 202303151122, "o": 42, "h": 42.1, "l": 42, "c": 42.1, "v": 5}, {"t": 202303151123, "o": 42, "h": 42, "l": 42, "c": 42, "v": 1}, {"t": 202303151126, "o": 41.95, "h": 41.95, "l": 41.95, "c": 41.95, "v": 10}, {"t": 202303151127, "o": 41.95, "h": 41.95, "l": 41.95, "c": 41.95, "v": 7}, {"t": 202303151138, "o": 42.05, "h": 42.1, "l": 42.05, "c": 42.1, "v": 3}, {"t": 202303151139, "o": 42, "h": 42.1, "l": 42, "c": 42.1, "v": 2}, {"t": 202303151140, "o": 42.1, "h": 42.1, "l": 42.1, "c": 42.1, "v": 2}, {"t": 202303151149, "o": 42.25, "h": 42.25, "l": 42.25, "c": 42.25, "v": 1}, {"t": 202303151158, "o": 42.2, "h": 42.2, "l": 42.2, "c": 42.2, "v": 2}, {"t": 202303151207, "o": 42, "h": 42, "l": 42, "c": 42, "v": 2}, {"t": 202303151211, "o": 42.05, "h": 42.2, "l": 42.05, "c": 42.2, "v": 5}, {"t": 202303151214, "o": 42.1, "h": 42.1, "l": 42.1, "c": 42.1, "v": 1}, {"t": 202303151220, "o": 42.05, "h": 42.05, "l": 42.05, "c": 42.05, "v": 17}, {"t": 202303151221, "o": 42, "h": 42, "l": 42, "c": 42, "v": 4}, {"t": 202303151225, "o": 41.95, "h": 42, "l": 41.95, "c": 42, "v": 2}, {"t": 202303151227, "o": 41.95, "h": 41.95, "l": 41.95, "c": 41.95, "v": 1}, {"t": 202303151228, "o": 42, "h": 42, "l": 42, "c": 42, "v": 1}, {"t": 202303151232, "o": 42.05, "h": 42.05, "l": 42.05, "c": 42.05, "v": 3}, {"t": 202303151236, "o": 42.15, "h": 42.15, "l": 42.15, "c": 42.15, "v": 1}, {"t": 202303151237, "o": 42.05, "h": 42.05, "l": 42.05, "c": 42.05, "v": 4}, {"t": 202303151243, "o": 42.05, "h": 42.1, "l": 42.05, "c": 42.1, "v": 3}, {"t": 202303151253, "o": 42, "h": 42, "l": 42, "c": 42, "v": 6}, {"t": 202303151257, "o": 42, "h": 42, "l": 41.95, "c": 41.95, "v": 3}, {"t": 202303151259, "o": 41.9, "h": 41.9, "l": 41.9, "c": 41.9, "v": 1}, {"t": 202303151300, "o": 41.95, "h": 41.95, "l": 41.95, "c": 41.95, "v": 3}, {"t": 202303151304, "o": 41.9, "h": 41.9, "l": 41.9, "c": 41.9, "v": 10}, {"t": 202303151305, "o": 41.9, "h": 42, "l": 41.9, "c": 42, "v": 14}, {"t": 202303151308, "o": 42, "h": 42, "l": 42, "c": 42, "v": 1}, {"t": 202303151309, "o": 42, "h": 42.05, "l": 42, "c": 42, "v": 3}, {"t": 202303151310, "o": 42, "h": 42, "l": 42, "c": 42, "v": 3}, {"t": 202303151311, "o": 42, "h": 42, "l": 42, "c": 42, "v": 2}, {"t": 202303151312, "o": 42, "h": 42.05, "l": 42, "c": 42.05, "v": 10}, {"t": 202303151313, "o": 42, "h": 42, "l": 42, "c": 42, "v": 11}, {"t": 202303151314, "o": 42, "h": 42, "l": 42, "c": 42, "v": 1}, {"t": 202303151316, "o": 42, "h": 42, "l": 42, "c": 42, "v": 1}, {"t": 202303151317, "o": 42.1, "h": 42.1, "l": 42.1, "c": 42.1, "v": 1}, {"t": 202303151321, "o": 41.95, "h": 41.95, "l": 41.95, "c": 41.95, "v": 1}, {"t": 202303151322, "o": 41.95, "h": 41.95, "l": 41.95, "c": 41.95, "v": 5}, {"t": 202303151323, "o": 42, "h": 42, "l": 42, "c": 42, "v": 4}, {"t": 202303151324, "o": 42, "h": 42.1, "l": 42, "c": 42.1, "v": 7}, {"t": 202303151325, "o": 42, "h": 42, "l": 42, "c": 42, "v": 1}, {"t": 202303151330, "o": 41.8, "h": 41.8, "l": 41.8, "c": 41.8, "v": 29}, {"t": 202303160901, "o": 41, "h": 41, "l": 41, "c": 41, "v": 28}, {"t": 202303160902, "o": 41.35, "h": 41.35, "l": 41.35, "c": 41.35, "v": 1}, {"t": 202303160905, "o": 41.5, "h": 41.65, "l": 41.5, "c": 41.55, "v": 15}, {"t": 202303160907, "o": 41.6, "h": 41.6, "l": 41.6, "c": 41.6, "v": 2}, {"t": 202303160908, "o": 41.6, "h": 41.7, "l": 41.6, "c": 41.7, "v": 5}, {"t": 202303160910, "o": 41.6, "h": 41.75, "l": 41.6, "c": 41.75, "v": 4}, {"t": 202303160911, "o": 41.9, "h": 41.9, "l": 41.9, "c": 41.9, "v": 7}, {"t": 202303160914, "o": 41.9, "h": 41.9, "l": 41.9, "c": 41.9, "v": 1}, {"t": 202303160916, "o": 41.7, "h": 41.7, "l": 41.7, "c": 41.7, "v": 1}, {"t": 202303160917, "o": 41.65, "h": 41.65, "l": 41.6, "c": 41.6, "v": 2}, {"t": 202303160918, "o": 41.55, "h": 41.75, "l": 41.45, "c": 41.45, "v": 33}, {"t": 202303160919, "o": 41.45, "h": 41.55, "l": 41.45, "c": 41.45, "v": 4}, {"t": 202303160920, "o": 41.4, "h": 41.4, "l": 41.4, "c": 41.4, "v": 2}, {"t": 202303160921, "o": 41.3, "h": 41.3, "l": 41.25, "c": 41.25, "v": 10}, {"t": 202303160922, "o": 41.2, "h": 41.2, "l": 41.1, "c": 41.2, "v": 6}, {"t": 202303160923, "o": 41.1, "h": 41.1, "l": 41.05, "c": 41.1, "v": 4}, {"t": 202303160924, "o": 41.1, "h": 41.2, "l": 41.1, "c": 41.1, "v": 6}, {"t": 202303160925, "o": 41.15, "h": 41.2, "l": 41.15, "c": 41.2, "v": 5}, {"t": 202303160926, "o": 41.2, "h": 41.3, "l": 41.2, "c": 41.3, "v": 9}, {"t": 202303160929, "o": 41.3, "h": 41.35, "l": 41.3, "c": 41.35, "v": 5}, {"t": 202303160931, "o": 41.35, "h": 41.35, "l": 41.3, "c": 41.3, "v": 3}, {"t": 202303160935, "o": 41.5, "h": 41.5, "l": 41.5, "c": 41.5, "v": 3}, {"t": 202303160941, "o": 41.4, "h": 41.4, "l": 41.4, "c": 41.4, "v": 4}, {"t": 202303160947, "o": 41.4, "h": 41.4, "l": 41.35, "c": 41.35, "v": 4}, {"t": 202303160948, "o": 41.3, "h": 41.4, "l": 41.3, "c": 41.4, "v": 6}, {"t": 202303160952, "o": 41.3, "h": 41.5, "l": 41.25, "c": 41.3, "v": 40}, {"t": 202303160955, "o": 41.2, "h": 41.2, "l": 41.2, "c": 41.2, "v": 10}, {"t": 202303160956, "o": 41.2, "h": 41.2, "l": 41.2, "c": 41.2, "v": 1}, {"t": 202303160958, "o": 41.15, "h": 41.15, "l": 41.1, "c": 41.1, "v": 11}, {"t": 202303160959, "o": 41.1, "h": 41.1, "l": 41.05, "c": 41.1, "v": 21}, {"t": 202303161000, "o": 41.1, "h": 41.1, "l": 41.1, "c": 41.1, "v": 1}, {"t": 202303161001, "o": 41, "h": 41, "l": 41, "c": 41, "v": 20}, {"t": 202303161002, "o": 41.1, "h": 41.35, "l": 41.1, "c": 41.35, "v": 5}, {"t": 202303161003, "o": 41.1, "h": 41.1, "l": 41, "c": 41, "v": 5}, {"t": 202303161004, "o": 41.1, "h": 41.1, "l": 41.1, "c": 41.1, "v": 1}, {"t": 202303161006, "o": 41.1, "h": 41.1, "l": 41.1, "c": 41.1, "v": 9}, {"t": 202303161009, "o": 41, "h": 41, "l": 41, "c": 41, "v": 7}, {"t": 202303161011, "o": 41, "h": 41, "l": 41, "c": 41, "v": 5}, {"t": 202303161012, "o": 40.95, "h": 40.95, "l": 40.9, "c": 40.9, "v": 5}, {"t": 202303161013, "o": 40.95, "h": 40.95, "l": 40.95, "c": 40.95, "v": 1}, {"t": 202303161015, "o": 40.9, "h": 40.9, "l": 40.9, "c": 40.9, "v": 7}, {"t": 202303161016, "o": 40.9, "h": 40.9, "l": 40.9, "c": 40.9, "v": 3}, {"t": 202303161018, "o": 40.95, "h": 40.95, "l": 40.95, "c": 40.95, "v": 2}, {"t": 202303161019, "o": 40.95, "h": 40.95, "l": 40.95, "c": 40.95, "v": 7}, {"t": 202303161024, "o": 41, "h": 41, "l": 41, "c": 41, "v": 1}, {"t": 202303161026, "o": 41, "h": 41.05, "l": 41, "c": 41.05, "v": 15}, {"t": 202303161027, "o": 41.05, "h": 41.05, "l": 41.05, "c": 41.05, "v": 3}, {"t": 202303161028, "o": 41.05, "h": 41.05, "l": 41, "c": 41, "v": 4}, {"t": 202303161031, "o": 41, "h": 41, "l": 41, "c": 41, "v": 2}, {"t": 202303161032, "o": 40.95, "h": 40.95, "l": 40.65, "c": 40.65, "v": 22}, {"t": 202303161036, "o": 40.8, "h": 40.8, "l": 40.8, "c": 40.8, "v": 1}, {"t": 202303161048, "o": 40.8, "h": 40.8, "l": 40.8, "c": 40.8, "v": 5}, {"t": 202303161050, "o": 40.85, "h": 40.85, "l": 40.85, "c": 40.85, "v": 1}, {"t": 202303161051, "o": 40.9, "h": 40.9, "l": 40.9, "c": 40.9, "v": 1}, {"t": 202303161053, "o": 40.8, "h": 40.8, "l": 40.75, "c": 40.75, "v": 12}, {"t": 202303161054, "o": 40.75, "h": 40.75, "l": 40.75, "c": 40.75, "v": 1}, {"t": 202303161057, "o": 40.75, "h": 40.75, "l": 40.75, "c": 40.75, "v": 5}, {"t": 202303161058, "o": 40.8, "h": 40.8, "l": 40.8, "c": 40.8, "v": 2}, {"t": 202303161110, "o": 40.8, "h": 40.8, "l": 40.75, "c": 40.75, "v": 15}, {"t": 202303161111, "o": 40.7, "h": 40.7, "l": 40.7, "c": 40.7, "v": 3}, {"t": 202303161113, "o": 40.7, "h": 40.7, "l": 40.7, "c": 40.7, "v": 9}, {"t": 202303161116, "o": 40.7, "h": 40.75, "l": 40.7, "c": 40.75, "v": 6}, {"t": 202303161119, "o": 40.7, "h": 40.7, "l": 40.65, "c": 40.65, "v": 9}, {"t": 202303161120, "o": 40.65, "h": 40.65, "l": 40.65, "c": 40.65, "v": 11}, {"t": 202303161121, "o": 40.6, "h": 40.6, "l": 40.6, "c": 40.6, "v": 2}, {"t": 202303161123, "o": 40.75, "h": 40.75, "l": 40.75, "c": 40.75, "v": 2}, {"t": 202303161124, "o": 40.65, "h": 40.65, "l": 40.6, "c": 40.6, "v": 5}, {"t": 202303161125, "o": 40.65, "h": 40.7, "l": 40.65, "c": 40.7, "v": 4}, {"t": 202303161127, "o": 40.6, "h": 40.6, "l": 40.6, "c": 40.6, "v": 1}, {"t": 202303161128, "o": 40.6, "h": 40.6, "l": 40.6, "c": 40.6, "v": 1}, {"t": 202303161131, "o": 40.55, "h": 40.55, "l": 40.55, "c": 40.55, "v": 3}, {"t": 202303161133, "o": 40.6, "h": 40.6, "l": 40.6, "c": 40.6, "v": 3}, {"t": 202303161134, "o": 40.7, "h": 40.7, "l": 40.6, "c": 40.6, "v": 2}, {"t": 202303161135, "o": 40.6, "h": 40.6, "l": 40.6, "c": 40.6, "v": 2}, {"t": 202303161137, "o": 40.55, "h": 40.55, "l": 40.55, "c": 40.55, "v": 6}, {"t": 202303161138, "o": 40.55, "h": 40.55, "l": 40.55, "c": 40.55, "v": 1}, {"t": 202303161140, "o": 40.55, "h": 40.55, "l": 40.55, "c": 40.55, "v": 3}, {"t": 202303161141, "o": 40.6, "h": 40.6, "l": 40.6, "c": 40.6, "v": 1}, {"t": 202303161143, "o": 40.5, "h": 40.5, "l": 40.5, "c": 40.5, "v": 17}, {"t": 202303161144, "o": 40.45, "h": 40.5, "l": 40.45, "c": 40.5, "v": 10}, {"t": 202303161152, "o": 40.5, "h": 40.5, "l": 40.5, "c": 40.5, "v": 1}, {"t": 202303161154, "o": 40.5, "h": 40.5, "l": 40.5, "c": 40.5, "v": 1}, {"t": 202303161156, "o": 40.5, "h": 40.55, "l": 40.5, "c": 40.55, "v": 5}, {"t": 202303161157, "o": 40.55, "h": 40.55, "l": 40.55, "c": 40.55, "v": 1}, {"t": 202303161158, "o": 40.55, "h": 40.55, "l": 40.55, "c": 40.55, "v": 1}, {"t": 202303161200, "o": 40.5, "h": 40.55, "l": 40.5, "c": 40.55, "v": 2}, {"t": 202303161205, "o": 40.55, "h": 40.6, "l": 40.55, "c": 40.6, "v": 7}, {"t": 202303161206, "o": 40.65, "h": 40.65, "l": 40.65, "c": 40.65, "v": 1}, {"t": 202303161208, "o": 40.65, "h": 40.65, "l": 40.65, "c": 40.65, "v": 1}, {"t": 202303161212, "o": 40.7, "h": 40.7, "l": 40.65, "c": 40.65, "v": 3}, {"t": 202303161219, "o": 40.6, "h": 40.6, "l": 40.6, "c": 40.6, "v": 7}, {"t": 202303161221, "o": 40.55, "h": 40.55, "l": 40.55, "c": 40.55, "v": 1}, {"t": 202303161225, "o": 40.55, "h": 40.55, "l": 40.55, "c": 40.55, "v": 2}, {"t": 202303161226, "o": 40.55, "h": 40.55, "l": 40.5, "c": 40.5, "v": 12}, {"t": 202303161227, "o": 40.55, "h": 40.55, "l": 40.55, "c": 40.55, "v": 1}, {"t": 202303161235, "o": 40.55, "h": 40.55, "l": 40.55, "c": 40.55, "v": 1}, {"t": 202303161236, "o": 40.5, "h": 40.5, "l": 40.5, "c": 40.5, "v": 1}, {"t": 202303161237, "o": 40.5, "h": 40.5, "l": 40.5, "c": 40.5, "v": 1}, {"t": 202303161240, "o": 40.55, "h": 40.55, "l": 40.55, "c": 40.55, "v": 3}, {"t": 202303161243, "o": 40.6, "h": 40.6, "l": 40.6, "c": 40.6, "v": 6}, {"t": 202303161246, "o": 40.65, "h": 40.65, "l": 40.65, "c": 40.65, "v": 1}, {"t": 202303161247, "o": 40.7, "h": 40.75, "l": 40.7, "c": 40.75, "v": 8}, {"t": 202303161249, "o": 40.75, "h": 40.75, "l": 40.75, "c": 40.75, "v": 1}, {"t": 202303161250, "o": 40.75, "h": 40.75, "l": 40.75, "c": 40.75, "v": 1}, {"t": 202303161252, "o": 40.75, "h": 40.75, "l": 40.75, "c": 40.75, "v": 18}, {"t": 202303161253, "o": 40.8, "h": 40.8, "l": 40.8, "c": 40.8, "v": 2}, {"t": 202303161254, "o": 40.8, "h": 40.9, "l": 40.8, "c": 40.9, "v": 7}, {"t": 202303161255, "o": 40.85, "h": 40.85, "l": 40.85, "c": 40.85, "v": 1}, {"t": 202303161256, "o": 40.9, "h": 40.9, "l": 40.9, "c": 40.9, "v": 1}, {"t": 202303161259, "o": 40.8, "h": 40.8, "l": 40.8, "c": 40.8, "v": 1}, {"t": 202303161301, "o": 40.8, "h": 40.8, "l": 40.8, "c": 40.8, "v": 1}, {"t": 202303161302, "o": 40.85, "h": 40.85, "l": 40.8, "c": 40.8, "v": 2}, {"t": 202303161304, "o": 40.8, "h": 40.8, "l": 40.8, "c": 40.8, "v": 1}, {"t": 202303161305, "o": 40.8, "h": 40.8, "l": 40.8, "c": 40.8, "v": 1}, {"t": 202303161306, "o": 40.8, "h": 40.85, "l": 40.8, "c": 40.85, "v": 8}, {"t": 202303161307, "o": 40.85, "h": 40.85, "l": 40.85, "c": 40.85, "v": 2}, {"t": 202303161308, "o": 40.85, "h": 40.85, "l": 40.85, "c": 40.85, "v": 1}, {"t": 202303161311, "o": 40.8, "h": 40.8, "l": 40.8, "c": 40.8, "v": 2}, {"t": 202303161312, "o": 40.8, "h": 40.9, "l": 40.8, "c": 40.9, "v": 13}, {"t": 202303161313, "o": 40.95, "h": 41, "l": 40.95, "c": 41, "v": 9}, {"t": 202303161314, "o": 40.95, "h": 40.95, "l": 40.95, "c": 40.95, "v": 1}, {"t": 202303161317, "o": 40.9, "h": 40.9, "l": 40.9, "c": 40.9, "v": 2}, {"t": 202303161320, "o": 40.85, "h": 40.85, "l": 40.85, "c": 40.85, "v": 1}, {"t": 202303161322, "o": 40.85, "h": 40.85, "l": 40.85, "c": 40.85, "v": 1}, {"t": 202303161323, "o": 40.85, "h": 40.85, "l": 40.85, "c": 40.85, "v": 1}, {"t": 202303161325, "o": 40.8, "h": 40.8, "l": 40.8, "c": 40.8, "v": 4}, {"t": 202303161330, "o": 40.75, "h": 40.75, "l": 40.75, "c": 40.75, "v": 23}, {"t": 202303170901, "o": 41.3, "h": 41.45, "l": 41.3, "c": 41.45, "v": 9}, {"t": 202303170902, "o": 41.5, "h": 41.6, "l": 41.5, "c": 41.6, "v": 9}, {"t": 202303170903, "o": 41.55, "h": 41.55, "l": 41.45, "c": 41.45, "v": 6}, {"t": 202303170904, "o": 41.35, "h": 41.35, "l": 41.35, "c": 41.35, "v": 2}, {"t": 202303170907, "o": 41.45, "h": 41.45, "l": 41.45, "c": 41.45, "v": 2}, {"t": 202303170908, "o": 41.45, "h": 41.45, "l": 41.45, "c": 41.45, "v": 2}, {"t": 202303170909, "o": 41.4, "h": 41.4, "l": 41.4, "c": 41.4, "v": 4}, {"t": 202303170910, "o": 41.35, "h": 41.35, "l": 41.2, "c": 41.2, "v": 5}, {"t": 202303170913, "o": 41.2, "h": 41.2, "l": 41.2, "c": 41.2, "v": 5}, {"t": 202303170914, "o": 41.2, "h": 41.2, "l": 41.2, "c": 41.2, "v": 1}, {"t": 202303170915, "o": 41.45, "h": 41.45, "l": 41.45, "c": 41.45, "v": 4}, {"t": 202303170916, "o": 41.4, "h": 41.4, "l": 41.4, "c": 41.4, "v": 1}, {"t": 202303170921, "o": 41.25, "h": 41.25, "l": 41.25, "c": 41.25, "v": 3}, {"t": 202303170924, "o": 41.25, "h": 41.25, "l": 41.2, "c": 41.2, "v": 5}, {"t": 202303170926, "o": 41.2, "h": 41.2, "l": 41.2, "c": 41.2, "v": 1}, {"t": 202303170928, "o": 41, "h": 41, "l": 41, "c": 41, "v": 1}, {"t": 202303170929, "o": 40.95, "h": 40.95, "l": 40.95, "c": 40.95, "v": 2}, {"t": 202303170930, "o": 40.95, "h": 40.95, "l": 40.95, "c": 40.95, "v": 8}, {"t": 202303170946, "o": 41.05, "h": 41.05, "l": 41.05, "c": 41.05, "v": 4}, {"t": 202303170952, "o": 41.1, "h": 41.1, "l": 41.1, "c": 41.1, "v": 1}, {"t": 202303170955, "o": 41.1, "h": 41.1, "l": 41, "c": 41, "v": 7}, {"t": 202303170957, "o": 41, "h": 41, "l": 41, "c": 41, "v": 1}, {"t": 202303171003, "o": 41.05, "h": 41.1, "l": 41.05, "c": 41.1, "v": 4}, {"t": 202303171005, "o": 41.05, "h": 41.05, "l": 41, "c": 41, "v": 2}, {"t": 202303171006, "o": 41, "h": 41, "l": 41, "c": 41, "v": 2}, {"t": 202303171009, "o": 41, "h": 41, "l": 41, "c": 41, "v": 1}, {"t": 202303171016, "o": 40.95, "h": 40.95, "l": 40.8, "c": 40.8, "v": 26}, {"t": 202303171018, "o": 40.8, "h": 40.8, "l": 40.8, "c": 40.8, "v": 5}, {"t": 202303171025, "o": 40.8, "h": 40.8, "l": 40.8, "c": 40.8, "v": 1}, {"t": 202303171026, "o": 40.75, "h": 40.75, "l": 40.75, "c": 40.75, "v": 1}, {"t": 202303171029, "o": 40.75, "h": 40.75, "l": 40.75, "c": 40.75, "v": 1}, {"t": 202303171030, "o": 40.75, "h": 40.75, "l": 40.6, "c": 40.6, "v": 18}, {"t": 202303171032, "o": 40.6, "h": 40.6, "l": 40.6, "c": 40.6, "v": 1}, {"t": 202303171035, "o": 40.6, "h": 40.6, "l": 40.6, "c": 40.6, "v": 4}, {"t": 202303171036, "o": 40.55, "h": 40.55, "l": 40.55, "c": 40.55, "v": 4}, {"t": 202303171037, "o": 40.55, "h": 40.55, "l": 40.5, "c": 40.5, "v": 14}, {"t": 202303171040, "o": 40.5, "h": 40.5, "l": 40.5, "c": 40.5, "v": 1}, {"t": 202303171044, "o": 40.5, "h": 40.5, "l": 40.5, "c": 40.5, "v": 4}, {"t": 202303171045, "o": 40.5, "h": 40.5, "l": 40.5, "c": 40.5, "v": 2}, {"t": 202303171051, "o": 40.6, "h": 40.6, "l": 40.6, "c": 40.6, "v": 10}, {"t": 202303171052, "o": 40.7, "h": 40.7, "l": 40.7, "c": 40.7, "v": 1}, {"t": 202303171053, "o": 40.75, "h": 40.75, "l": 40.75, "c": 40.75, "v": 3}, {"t": 202303171055, "o": 40.7, "h": 40.75, "l": 40.7, "c": 40.75, "v": 6}, {"t": 202303171059, "o": 40.8, "h": 40.8, "l": 40.8, "c": 40.8, "v": 2}, {"t": 202303171100, "o": 40.8, "h": 40.8, "l": 40.75, "c": 40.75, "v": 4}, {"t": 202303171107, "o": 41, "h": 41, "l": 41, "c": 41, "v": 2}, {"t": 202303171109, "o": 41, "h": 41, "l": 41, "c": 41, "v": 7}, {"t": 202303171112, "o": 41.05, "h": 41.2, "l": 41.05, "c": 41.2, "v": 6}, {"t": 202303171117, "o": 41.15, "h": 41.15, "l": 41.15, "c": 41.15, "v": 1}, {"t": 202303171127, "o": 41.1, "h": 41.1, "l": 41.1, "c": 41.1, "v": 3}, {"t": 202303171136, "o": 41, "h": 41, "l": 41, "c": 41, "v": 1}, {"t": 202303171153, "o": 41.15, "h": 41.15, "l": 41.15, "c": 41.15, "v": 1}, {"t": 202303171200, "o": 41, "h": 41, "l": 41, "c": 41, "v": 1}, {"t": 202303171214, "o": 41.1, "h": 41.1, "l": 41.1, "c": 41.1, "v": 1}, {"t": 202303171217, "o": 41.1, "h": 41.1, "l": 41.1, "c": 41.1, "v": 8}, {"t": 202303171219, "o": 41.05, "h": 41.05, "l": 41.05, "c": 41.05, "v": 1}, {"t": 202303171220, "o": 41.05, "h": 41.05, "l": 41.05, "c": 41.05, "v": 1}, {"t": 202303171225, "o": 41, "h": 41.1, "l": 41, "c": 41.1, "v": 16}, {"t": 202303171232, "o": 41.1, "h": 41.1, "l": 41.1, "c": 41.1, "v": 5}, {"t": 202303171237, "o": 41.1, "h": 41.1, "l": 41.1, "c": 41.1, "v": 12}, {"t": 202303171238, "o": 41.15, "h": 41.15, "l": 41.15, "c": 41.15, "v": 2}, {"t": 202303171242, "o": 41.1, "h": 41.1, "l": 41.1, "c": 41.1, "v": 1}, {"t": 202303171247, "o": 41.1, "h": 41.1, "l": 41.1, "c": 41.1, "v": 3}, {"t": 202303171250, "o": 41.1, "h": 41.1, "l": 41.1, "c": 41.1, "v": 1}, {"t": 202303171251, "o": 41.1, "h": 41.1, "l": 41.1, "c": 41.1, "v": 4}, {"t": 202303171252, "o": 41.1, "h": 41.1, "l": 41.1, "c": 41.1, "v": 1}, {"t": 202303171255, "o": 41.1, "h": 41.1, "l": 41.1, "c": 41.1, "v": 3}, {"t": 202303171259, "o": 41.1, "h": 41.1, "l": 41.1, "c": 41.1, "v": 1}, {"t": 202303171301, "o": 41.1, "h": 41.1, "l": 41.1, "c": 41.1, "v": 1}, {"t": 202303171311, "o": 41.05, "h": 41.05, "l": 41.05, "c": 41.05, "v": 1}, {"t": 202303171316, "o": 41.05, "h": 41.1, "l": 41.05, "c": 41.1, "v": 9}, {"t": 202303171317, "o": 41.05, "h": 41.05, "l": 41, "c": 41, "v": 10}, {"t": 202303171318, "o": 41.05, "h": 41.05, "l": 41.05, "c": 41.05, "v": 1}, {"t": 202303171319, "o": 41, "h": 41, "l": 41, "c": 41, "v": 10}, {"t": 202303171320, "o": 41, "h": 41, "l": 41, "c": 41, "v": 5}, {"t": 202303171321, "o": 41.05, "h": 41.05, "l": 41.05, "c": 41.05, "v": 3}, {"t": 202303171322, "o": 41.1, "h": 41.1, "l": 41.1, "c": 41.1, "v": 1}, {"t": 202303171324, "o": 41.1, "h": 41.1, "l": 41.1, "c": 41.1, "v": 1}, {"t": 202303171330, "o": 40.95, "h": 40.95, "l": 40.95, "c": 40.95, "v": 16}, {"t": 202303210901, "o": 41.45, "h": 41.45, "l": 41.45, "c": 41.45, "v": 6}, {"t": 202303210907, "o": 41.45, "h": 41.45, "l": 41.35, "c": 41.35, "v": 23}, {"t": 202303210908, "o": 41.3, "h": 41.3, "l": 41.3, "c": 41.3, "v": 3}, {"t": 202303210910, "o": 41.25, "h": 41.25, "l": 41.25, "c": 41.25, "v": 2}, {"t": 202303210916, "o": 41.25, "h": 41.25, "l": 41.25, "c": 41.25, "v": 1}, {"t": 202303210918, "o": 41.3, "h": 41.3, "l": 41.3, "c": 41.3, "v": 1}, {"t": 202303210919, "o": 41.35, "h": 41.35, "l": 41.35, "c": 41.35, "v": 3}, {"t": 202303210922, "o": 41.35, "h": 41.35, "l": 41.35, "c": 41.35, "v": 1}, {"t": 202303210927, "o": 41.45, "h": 41.45, "l": 41.45, "c": 41.45, "v": 4}, {"t": 202303210928, "o": 41.5, "h": 41.5, "l": 41.5, "c": 41.5, "v": 1}, {"t": 202303210931, "o": 41.45, "h": 41.45, "l": 41.45, "c": 41.45, "v": 3}, {"t": 202303210935, "o": 41.35, "h": 41.35, "l": 41.35, "c": 41.35, "v": 1}, {"t": 202303210936, "o": 41.45, "h": 41.5, "l": 41.45, "c": 41.5, "v": 13}, {"t": 202303210937, "o": 41.5, "h": 41.55, "l": 41.5, "c": 41.55, "v": 30}, {"t": 202303210938, "o": 41.55, "h": 41.55, "l": 41.55, "c": 41.55, "v": 2}, {"t": 202303210939, "o": 41.55, "h": 41.55, "l": 41.55, "c": 41.55, "v": 2}, {"t": 202303210941, "o": 41.6, "h": 41.6, "l": 41.6, "c": 41.6, "v": 6}, {"t": 202303210942, "o": 41.6, "h": 41.6, "l": 41.6, "c": 41.6, "v": 1}, {"t": 202303210943, "o": 41.65, "h": 41.65, "l": 41.65, "c": 41.65, "v": 11}, {"t": 202303210944, "o": 41.65, "h": 41.65, "l": 41.65, "c": 41.65, "v": 12}, {"t": 202303210946, "o": 41.65, "h": 41.65, "l": 41.65, "c": 41.65, "v": 8}, {"t": 202303210947, "o": 41.6, "h": 41.6, "l": 41.6, "c": 41.6, "v": 1}, {"t": 202303210952, "o": 41.6, "h": 41.6, "l": 41.6, "c": 41.6, "v": 2}, {"t": 202303211000, "o": 41.65, "h": 41.75, "l": 41.65, "c": 41.75, "v": 6}, {"t": 202303211001, "o": 41.6, "h": 41.6, "l": 41.6, "c": 41.6, "v": 6}, {"t": 202303211010, "o": 41.55, "h": 41.55, "l": 41.55, "c": 41.55, "v": 3}, {"t": 202303211016, "o": 41.6, "h": 41.6, "l": 41.6, "c": 41.6, "v": 1}, {"t": 202303211017, "o": 41.6, "h": 41.6, "l": 41.6, "c": 41.6, "v": 2}, {"t": 202303211033, "o": 41.55, "h": 41.55, "l": 41.5, "c": 41.5, "v": 6}, {"t": 202303211035, "o": 41.55, "h": 41.55, "l": 41.55, "c": 41.55, "v": 2}]}}}