{"ta": [{"t": 202302010925, "o": 78.1, "h": 78.1, "l": 78.1, "c": 78.1, "v": 5.0}, {"t": 202302011005, "o": 78.2, "h": 78.2, "l": 78.2, "c": 78.2, "v": 1.0}, {"t": 202302011030, "o": 78.3, "h": 78.3, "l": 78.3, "c": 78.3, "v": 1.0}, {"t": 202302011035, "o": 78.8, "h": 78.8, "l": 78.8, "c": 78.8, "v": 1.0}, {"t": 202302011040, "o": 78.8, "h": 78.8, "l": 78.8, "c": 78.8, "v": 2.0}, {"t": 202302011050, "o": 78.8, "h": 78.8, "l": 78.8, "c": 78.8, "v": 1.0}, {"t": 202302011105, "o": 78.9, "h": 78.9, "l": 78.9, "c": 78.9, "v": 1.0}, {"t": 202302011125, "o": 78.9, "h": 78.9, "l": 78.9, "c": 78.9, "v": 5.0}, {"t": 202302011130, "o": 79.0, "h": 79.4, "l": 79.0, "c": 79.4, "v": 5.0}, {"t": 202302011140, "o": 79.4, "h": 79.4, "l": 79.4, "c": 79.4, "v": 1.0}, {"t": 202302011145, "o": 79.4, "h": 79.4, "l": 79.4, "c": 79.4, "v": 2.0}, {"t": 202302011150, "o": 79.5, "h": 79.5, "l": 79.5, "c": 79.5, "v": 5.0}, {"t": 202302011210, "o": 79.5, "h": 79.5, "l": 79.4, "c": 79.4, "v": 3.0}, {"t": 202302011215, "o": 79.0, "h": 79.0, "l": 79.0, "c": 79.0, "v": 1.0}, {"t": 202302011225, "o": 79.3, "h": 79.3, "l": 79.1, "c": 79.1, "v": 2.0}, {"t": 202302011235, "o": 79.1, "h": 79.1, "l": 79.0, "c": 79.0, "v": 4.0}, {"t": 202302011240, "o": 79.3, "h": 79.3, "l": 79.0, "c": 79.0, "v": 6.0}, {"t": 202302011300, "o": 79.0, "h": 79.0, "l": 79.0, "c": 79.0, "v": 1.0}, {"t": 202302011305, "o": 79.0, "h": 79.0, "l": 79.0, "c": 79.0, "v": 3.0}, {"t": 202302011310, "o": 79.3, "h": 79.6, "l": 79.3, "c": 79.5, "v": 10.0}, {"t": 202302011315, "o": 79.5, "h": 79.5, "l": 79.5, "c": 79.5, "v": 1.0}, {"t": 202302011325, "o": 79.5, "h": 79.5, "l": 79.5, "c": 79.5, "v": 1.0}, {"t": 202302011330, "o": 79.5, "h": 79.5, "l": 79.5, "c": 79.5, "v": 1.0}, {"t": 202302020905, "o": 79.5, "h": 79.5, "l": 79.5, "c": 79.5, "v": 5.0}, {"t": 202302020915, "o": 79.5, "h": 79.5, "l": 79.5, "c": 79.5, "v": 2.0}, {"t": 202302020925, "o": 79.4, "h": 79.4, "l": 79.4, "c": 79.4, "v": 2.0}, {"t": 202302020940, "o": 79.4, "h": 79.4, "l": 79.4, "c": 79.4, "v": 2.0}, {"t": 202302020950, "o": 79.4, "h": 79.4, "l": 79.4, "c": 79.4, "v": 2.0}, {"t": 202302020955, "o": 79.1, "h": 79.1, "l": 79.1, "c": 79.1, "v": 1.0}, {"t": 202302021030, "o": 79.5, "h": 79.9, "l": 79.4, "c": 79.9, "v": 13.0}, {"t": 202302021050, "o": 79.9, "h": 79.9, "l": 79.9, "c": 79.9, "v": 1.0}, {"t": 202302021145, "o": 79.7, "h": 79.8, "l": 79.7, "c": 79.8, "v": 2.0}, {"t": 202302021200, "o": 79.8, "h": 79.9, "l": 79.8, "c": 79.9, "v": 2.0}, {"t": 202302021215, "o": 79.8, "h": 79.8, "l": 79.8, "c": 79.8, "v": 1.0}, {"t": 202302021225, "o": 79.9, "h": 79.9, "l": 79.9, "c": 79.9, "v": 3.0}, {"t": 202302021250, "o": 79.9, "h": 79.9, "l": 79.9, "c": 79.9, "v": 3.0}, {"t": 202302021310, "o": 80.0, "h": 80.0, "l": 79.9, "c": 79.9, "v": 3.0}, {"t": 202302021325, "o": 79.9, "h": 79.9, "l": 79.9, "c": 79.9, "v": 1.0}, {"t": 202302021330, "o": 79.9, "h": 79.9, "l": 79.9, "c": 79.9, "v": 2.0}, {"t": 202302030905, "o": 80.0, "h": 80.0, "l": 80.0, "c": 80.0, "v": 1.0}, {"t": 202302030910, "o": 79.9, "h": 79.9, "l": 79.6, "c": 79.6, "v": 4.0}, {"t": 202302030925, "o": 79.5, "h": 79.5, "l": 79.5, "c": 79.5, "v": 5.0}, {"t": 202302030935, "o": 79.5, "h": 79.5, "l": 79.5, "c": 79.5, "v": 1.0}, {"t": 202302030940, "o": 79.9, "h": 79.9, "l": 79.9, "c": 79.9, "v": 1.0}, {"t": 202302031035, "o": 79.9, "h": 79.9, "l": 79.9, "c": 79.9, "v": 1.0}, {"t": 202302031125, "o": 79.8, "h": 79.8, "l": 79.8, "c": 79.8, "v": 1.0}, {"t": 202302031210, "o": 79.6, "h": 79.6, "l": 79.6, "c": 79.6, "v": 6.0}, {"t": 202302031215, "o": 79.8, "h": 79.8, "l": 79.8, "c": 79.8, "v": 1.0}, {"t": 202302031310, "o": 79.6, "h": 79.6, "l": 79.6, "c": 79.6, "v": 1.0}, {"t": 202302031320, "o": 79.6, "h": 79.6, "l": 79.5, "c": 79.5, "v": 11.0}, {"t": 202302031325, "o": 79.1, "h": 79.1, "l": 79.1, "c": 79.1, "v": 3.0}, {"t": 202302031330, "o": 79.8, "h": 79.8, "l": 79.8, "c": 79.8, "v": 1.0}, {"t": 202302060905, "o": 79.8, "h": 79.8, "l": 79.8, "c": 79.8, "v": 1.0}, {"t": 202302060910, "o": 78.6, "h": 78.6, "l": 78.6, "c": 78.6, "v": 9.0}, {"t": 202302060915, "o": 78.7, "h": 78.7, "l": 78.7, "c": 78.7, "v": 3.0}, {"t": 202302060920, "o": 78.7, "h": 78.7, "l": 78.7, "c": 78.7, "v": 1.0}, {"t": 202302060935, "o": 78.8, "h": 78.8, "l": 78.8, "c": 78.8, "v": 3.0}, {"t": 202302061015, "o": 79.6, "h": 79.7, "l": 79.6, "c": 79.7, "v": 3.0}, {"t": 202302061020, "o": 79.7, "h": 80.0, "l": 79.7, "c": 80.0, "v": 14.0}, {"t": 202302061025, "o": 79.9, "h": 79.9, "l": 79.9, "c": 79.9, "v": 1.0}, {"t": 202302061030, "o": 80.0, "h": 80.0, "l": 79.9, "c": 79.9, "v": 4.0}, {"t": 202302061100, "o": 79.9, "h": 79.9, "l": 79.9, "c": 79.9, "v": 1.0}, {"t": 202302061115, "o": 79.9, "h": 79.9, "l": 79.9, "c": 79.9, "v": 1.0}], "quote": [{"t": 202302061113, "ind": 18.0, "indp": 45.0, "exd": 22.0, "exdp": 55.0}]}