{"ta": [{"t": 202302010905, "o": 71.3, "h": 71.3, "l": 71.3, "c": 71.3, "v": 1.0}, {"t": 202302010925, "o": 71.4, "h": 71.4, "l": 71.3, "c": 71.3, "v": 3.0}, {"t": 202302010930, "o": 71.3, "h": 71.3, "l": 71.3, "c": 71.3, "v": 1.0}, {"t": 202302010950, "o": 71.4, "h": 71.4, "l": 71.4, "c": 71.4, "v": 2.0}, {"t": 202302011005, "o": 71.5, "h": 71.5, "l": 71.5, "c": 71.5, "v": 5.0}, {"t": 202302011025, "o": 71.5, "h": 71.5, "l": 71.5, "c": 71.5, "v": 1.0}, {"t": 202302011050, "o": 71.4, "h": 71.5, "l": 71.3, "c": 71.5, "v": 5.0}, {"t": 202302011055, "o": 71.4, "h": 71.4, "l": 71.3, "c": 71.3, "v": 3.0}, {"t": 202302011100, "o": 71.4, "h": 71.4, "l": 71.4, "c": 71.4, "v": 2.0}, {"t": 202302011135, "o": 71.4, "h": 71.4, "l": 71.3, "c": 71.3, "v": 2.0}, {"t": 202302011145, "o": 71.4, "h": 71.4, "l": 71.4, "c": 71.4, "v": 2.0}, {"t": 202302011150, "o": 71.4, "h": 71.4, "l": 71.4, "c": 71.4, "v": 3.0}, {"t": 202302011200, "o": 71.4, "h": 71.4, "l": 71.4, "c": 71.4, "v": 2.0}, {"t": 202302011210, "o": 71.3, "h": 71.3, "l": 71.2, "c": 71.2, "v": 3.0}, {"t": 202302011230, "o": 71.3, "h": 71.3, "l": 71.3, "c": 71.3, "v": 1.0}, {"t": 202302011235, "o": 71.3, "h": 71.3, "l": 71.3, "c": 71.3, "v": 1.0}, {"t": 202302011240, "o": 71.3, "h": 71.4, "l": 71.3, "c": 71.4, "v": 5.0}, {"t": 202302011245, "o": 71.4, "h": 71.4, "l": 71.4, "c": 71.4, "v": 1.0}, {"t": 202302011255, "o": 71.4, "h": 71.4, "l": 71.3, "c": 71.3, "v": 2.0}, {"t": 202302011310, "o": 71.3, "h": 71.3, "l": 71.3, "c": 71.3, "v": 1.0}, {"t": 202302011315, "o": 71.3, "h": 71.3, "l": 71.3, "c": 71.3, "v": 3.0}, {"t": 202302011320, "o": 71.2, "h": 71.2, "l": 71.2, "c": 71.2, "v": 2.0}, {"t": 202302011325, "o": 71.4, "h": 71.4, "l": 71.3, "c": 71.3, "v": 4.0}, {"t": 202302011330, "o": 71.4, "h": 71.4, "l": 71.4, "c": 71.4, "v": 3.0}, {"t": 202302020905, "o": 71.4, "h": 71.4, "l": 71.4, "c": 71.4, "v": 1.0}, {"t": 202302020915, "o": 71.7, "h": 71.7, "l": 71.7, "c": 71.7, "v": 1.0}, {"t": 202302020925, "o": 71.6, "h": 71.6, "l": 71.6, "c": 71.6, "v": 1.0}, {"t": 202302020935, "o": 71.8, "h": 71.8, "l": 71.8, "c": 71.8, "v": 1.0}, {"t": 202302021000, "o": 71.7, "h": 71.8, "l": 71.7, "c": 71.8, "v": 6.0}, {"t": 202302021020, "o": 71.8, "h": 71.9, "l": 71.6, "c": 71.6, "v": 3.0}, {"t": 202302021025, "o": 71.9, "h": 71.9, "l": 71.5, "c": 71.5, "v": 10.0}, {"t": 202302021035, "o": 71.5, "h": 71.5, "l": 71.5, "c": 71.5, "v": 5.0}, {"t": 202302021040, "o": 71.5, "h": 71.5, "l": 71.5, "c": 71.5, "v": 1.0}, {"t": 202302021055, "o": 71.5, "h": 71.5, "l": 71.5, "c": 71.5, "v": 1.0}, {"t": 202302021100, "o": 71.6, "h": 71.6, "l": 71.5, "c": 71.5, "v": 3.0}, {"t": 202302021145, "o": 71.6, "h": 71.6, "l": 71.6, "c": 71.6, "v": 3.0}, {"t": 202302021200, "o": 71.8, "h": 71.8, "l": 71.8, "c": 71.8, "v": 7.0}, {"t": 202302021205, "o": 71.8, "h": 71.8, "l": 71.7, "c": 71.7, "v": 8.0}, {"t": 202302021300, "o": 71.8, "h": 71.8, "l": 71.8, "c": 71.8, "v": 2.0}, {"t": 202302021310, "o": 71.8, "h": 71.9, "l": 71.8, "c": 71.9, "v": 2.0}, {"t": 202302021320, "o": 71.9, "h": 71.9, "l": 71.9, "c": 71.9, "v": 1.0}, {"t": 202302021330, "o": 72.0, "h": 72.0, "l": 72.0, "c": 72.0, "v": 8.0}, {"t": 202302030905, "o": 72.0, "h": 72.2, "l": 72.0, "c": 72.1, "v": 5.0}, {"t": 202302030910, "o": 72.0, "h": 72.0, "l": 72.0, "c": 72.0, "v": 2.0}, {"t": 202302030915, "o": 72.0, "h": 72.0, "l": 72.0, "c": 72.0, "v": 7.0}, {"t": 202302030920, "o": 72.0, "h": 72.0, "l": 72.0, "c": 72.0, "v": 3.0}, {"t": 202302030930, "o": 72.0, "h": 72.0, "l": 72.0, "c": 72.0, "v": 1.0}, {"t": 202302030935, "o": 72.2, "h": 72.2, "l": 72.2, "c": 72.2, "v": 3.0}, {"t": 202302030940, "o": 72.1, "h": 72.1, "l": 72.1, "c": 72.1, "v": 1.0}, {"t": 202302030955, "o": 72.0, "h": 72.0, "l": 72.0, "c": 72.0, "v": 2.0}, {"t": 202302031005, "o": 71.9, "h": 71.9, "l": 71.9, "c": 71.9, "v": 1.0}, {"t": 202302031010, "o": 71.9, "h": 71.9, "l": 71.9, "c": 71.9, "v": 1.0}, {"t": 202302031015, "o": 72.0, "h": 72.0, "l": 72.0, "c": 72.0, "v": 2.0}, {"t": 202302031020, "o": 72.0, "h": 72.0, "l": 72.0, "c": 72.0, "v": 1.0}, {"t": 202302031025, "o": 71.9, "h": 72.0, "l": 71.9, "c": 72.0, "v": 5.0}, {"t": 202302031035, "o": 72.0, "h": 72.0, "l": 72.0, "c": 72.0, "v": 4.0}, {"t": 202302031040, "o": 72.0, "h": 72.0, "l": 72.0, "c": 72.0, "v": 1.0}, {"t": 202302031105, "o": 72.1, "h": 72.5, "l": 72.1, "c": 72.5, "v": 9.0}, {"t": 202302031110, "o": 72.5, "h": 72.5, "l": 72.5, "c": 72.5, "v": 1.0}, {"t": 202302031120, "o": 72.3, "h": 72.5, "l": 72.3, "c": 72.5, "v": 6.0}, {"t": 202302031125, "o": 72.4, "h": 72.4, "l": 72.4, "c": 72.4, "v": 1.0}, {"t": 202302031140, "o": 72.3, "h": 72.3, "l": 72.3, "c": 72.3, "v": 2.0}, {"t": 202302031150, "o": 72.4, "h": 72.4, "l": 72.4, "c": 72.4, "v": 1.0}, {"t": 202302031200, "o": 72.4, "h": 72.4, "l": 72.4, "c": 72.4, "v": 2.0}, {"t": 202302031215, "o": 72.3, "h": 72.3, "l": 72.3, "c": 72.3, "v": 2.0}, {"t": 202302031220, "o": 72.5, "h": 72.5, "l": 72.2, "c": 72.2, "v": 4.0}, {"t": 202302031305, "o": 72.2, "h": 72.2, "l": 72.2, "c": 72.2, "v": 2.0}, {"t": 202302031310, "o": 72.2, "h": 72.3, "l": 72.2, "c": 72.3, "v": 2.0}, {"t": 202302031315, "o": 72.3, "h": 72.3, "l": 72.3, "c": 72.3, "v": 2.0}, {"t": 202302031320, "o": 72.3, "h": 72.3, "l": 72.2, "c": 72.2, "v": 2.0}, {"t": 202302031325, "o": 72.4, "h": 72.4, "l": 72.4, "c": 72.4, "v": 2.0}, {"t": 202302031330, "o": 72.5, "h": 72.5, "l": 72.5, "c": 72.5, "v": 7.0}, {"t": 202302060905, "o": 72.5, "h": 72.5, "l": 72.5, "c": 72.5, "v": 6.0}, {"t": 202302060910, "o": 72.6, "h": 72.6, "l": 72.6, "c": 72.6, "v": 2.0}, {"t": 202302060915, "o": 72.6, "h": 72.6, "l": 72.3, "c": 72.3, "v": 6.0}, {"t": 202302060920, "o": 72.3, "h": 72.7, "l": 72.3, "c": 72.7, "v": 10.0}, {"t": 202302060925, "o": 72.6, "h": 72.6, "l": 72.6, "c": 72.6, "v": 5.0}, {"t": 202302060930, "o": 72.3, "h": 72.3, "l": 72.3, "c": 72.3, "v": 1.0}, {"t": 202302060940, "o": 72.5, "h": 72.5, "l": 72.5, "c": 72.5, "v": 3.0}, {"t": 202302060945, "o": 72.5, "h": 72.5, "l": 72.5, "c": 72.5, "v": 2.0}, {"t": 202302061010, "o": 72.7, "h": 72.7, "l": 72.7, "c": 72.7, "v": 6.0}, {"t": 202302061015, "o": 72.7, "h": 72.7, "l": 72.7, "c": 72.7, "v": 1.0}, {"t": 202302061020, "o": 72.7, "h": 72.7, "l": 72.7, "c": 72.7, "v": 1.0}, {"t": 202302061025, "o": 72.7, "h": 73.0, "l": 72.7, "c": 73.0, "v": 12.0}, {"t": 202302061030, "o": 73.1, "h": 73.2, "l": 72.6, "c": 73.2, "v": 11.0}, {"t": 202302061040, "o": 73.2, "h": 73.2, "l": 73.2, "c": 73.2, "v": 1.0}, {"t": 202302061045, "o": 73.3, "h": 73.4, "l": 72.8, "c": 72.8, "v": 6.0}, {"t": 202302061055, "o": 72.9, "h": 73.0, "l": 72.9, "c": 72.9, "v": 4.0}, {"t": 202302061105, "o": 72.8, "h": 72.8, "l": 72.8, "c": 72.8, "v": 2.0}, {"t": 202302061110, "o": 72.9, "h": 73.2, "l": 72.9, "c": 73.2, "v": 9.0}, {"t": 202302061120, "o": 73.2, "h": 73.3, "l": 73.2, "c": 73.3, "v": 5.0}, {"t": 202302061135, "o": 73.3, "h": 73.3, "l": 73.3, "c": 73.3, "v": 5.0}, {"t": 202302061145, "o": 73.4, "h": 73.4, "l": 73.2, "c": 73.2, "v": 2.0}, {"t": 202302061155, "o": 73.4, "h": 73.5, "l": 73.4, "c": 73.4, "v": 9.0}, {"t": 202302061200, "o": 73.5, "h": 73.6, "l": 73.5, "c": 73.5, "v": 4.0}, {"t": 202302061205, "o": 73.5, "h": 73.6, "l": 73.5, "c": 73.5, "v": 26.0}, {"t": 202302061210, "o": 73.6, "h": 73.6, "l": 73.6, "c": 73.6, "v": 9.0}, {"t": 202302061215, "o": 73.6, "h": 73.6, "l": 73.5, "c": 73.5, "v": 4.0}, {"t": 202302061220, "o": 73.5, "h": 73.5, "l": 73.5, "c": 73.5, "v": 1.0}, {"t": 202302061225, "o": 73.5, "h": 73.5, "l": 73.5, "c": 73.5, "v": 8.0}], "quote": [{"t": 202302061221, "ind": 46.0, "indp": 28.57, "exd": 115.0, "exdp": 71.43}]}